audiotools/__init__.py
audiotools/_accuraterip.cpython-35m-arm-linux-gnueabihf.so
audiotools/_ogg.cpython-35m-arm-linux-gnueabihf.so
audiotools/accuraterip.py
audiotools/aiff.py
audiotools/ape.py
audiotools/au.py
audiotools/bitstream.cpython-35m-arm-linux-gnueabihf.so
audiotools/cdtoc.py
audiotools/coverartarchive.py
audiotools/decoders.cpython-35m-arm-linux-gnueabihf.so
audiotools/encoders.cpython-35m-arm-linux-gnueabihf.so
audiotools/flac.py
audiotools/freedb.py
audiotools/id3.py
audiotools/id3v1.py
audiotools/image.py
audiotools/m4a.py
audiotools/m4a_atoms.py
audiotools/mp3.py
audiotools/mpc.py
audiotools/musicbrainz.py
audiotools/ogg.py
audiotools/opus.py
audiotools/output.cpython-35m-arm-linux-gnueabihf.so
audiotools/pcm.cpython-35m-arm-linux-gnueabihf.so
audiotools/pcmconverter.cpython-35m-arm-linux-gnueabihf.so
audiotools/player.py
audiotools/replaygain.cpython-35m-arm-linux-gnueabihf.so
audiotools/speex.py
audiotools/text.py
audiotools/tta.py
audiotools/ui.py
audiotools/vorbis.py
audiotools/vorbiscomment.py
audiotools/wav.py
audiotools/wavpack.py
audiotools/cue/__init__.py
audiotools/cue/tokrules.py
audiotools/cue/yaccrules.py
audiotools/ply/__init__.py
audiotools/ply/lex.py
audiotools/ply/yacc.py
audiotools/toc/__init__.py
audiotools/toc/tokrules.py
audiotools/toc/yaccrules.py
pyaudiotools-3.2a2.data/scripts/audiotools-config
pyaudiotools-3.2a2.data/scripts/coverbrowse
pyaudiotools-3.2a2.data/scripts/coverdump
pyaudiotools-3.2a2.data/scripts/covertag
pyaudiotools-3.2a2.data/scripts/track2cdda
pyaudiotools-3.2a2.data/scripts/track2track
pyaudiotools-3.2a2.data/scripts/trackcat
pyaudiotools-3.2a2.data/scripts/trackcmp
pyaudiotools-3.2a2.data/scripts/trackinfo
pyaudiotools-3.2a2.data/scripts/tracklength
pyaudiotools-3.2a2.data/scripts/tracklint
pyaudiotools-3.2a2.data/scripts/trackplay
pyaudiotools-3.2a2.data/scripts/trackrename
pyaudiotools-3.2a2.data/scripts/tracksplit
pyaudiotools-3.2a2.dist-info/DESCRIPTION.rst
pyaudiotools-3.2a2.dist-info/METADATA
pyaudiotools-3.2a2.dist-info/RECORD
pyaudiotools-3.2a2.dist-info/WHEEL
pyaudiotools-3.2a2.dist-info/metadata.json
pyaudiotools-3.2a2.dist-info/top_level.txt
