Metadata-Version: 2.0
Name: pyaudiotools
Version: 3.2a2
Summary: A collection of audio handling utilities
Home-page: http://audiotools.sourceforge.net
Author: Brian Langenberger
Author-email: tuffy@users.sourceforge.net
License: GPLv2+
Download-URL: http://sourceforge.net/projects/audiotools/files/
Platform: POSIX
Platform: Linux
Platform: OS X
Classifier: Development Status :: 5 - Production/Stable
Classifier: Environment :: Console
Classifier: Intended Audience :: Developers
Classifier: Intended Audience :: End Users/Desktop
Classifier: License :: OSI Approved :: GNU General Public License v2 or later (GPLv2+)
Classifier: Operating System :: MacOS :: MacOS X
Classifier: Operating System :: POSIX
Classifier: Operating System :: POSIX :: Linux
Classifier: Programming Language :: C
Classifier: Programming Language :: Python :: 2.7
Classifier: Programming Language :: Python :: 3.3
Classifier: Programming Language :: Python :: 3.4
Classifier: Topic :: Multimedia :: Sound/Audio
Classifier: Topic :: Multimedia :: Sound/Audio :: CD Audio
Classifier: Topic :: Multimedia :: Sound/Audio :: CD Audio :: CD Playing
Classifier: Topic :: Multimedia :: Sound/Audio :: CD Audio :: CD Ripping
Classifier: Topic :: Multimedia :: Sound/Audio :: CD Audio :: CD Writing
Classifier: Topic :: Multimedia :: Sound/Audio :: Conversion
Classifier: Topic :: Multimedia :: Sound/Audio :: Players
Classifier: Topic :: Software Development :: Libraries :: Python Modules
